wslPath/__init__.py
wslPath/main.py
wslPath-0.4.2.dist-info/LICENSE
wslPath-0.4.2.dist-info/METADATA
wslPath-0.4.2.dist-info/WHEEL
wslPath-0.4.2.dist-info/top_level.txt
wslPath-0.4.2.dist-info/RECORD
