Metadata-Version: 2.1
Name: wslPath
Version: 0.4.2
Summary: Python module to convert between Windows and POSIX path
Home-page: https://github.com/akikuno/wslPath
Author: Akihiro Kuno
Author-email: akuno@md.tsukuba.ac.jp
Classifier: Programming Language :: Python :: 3
Classifier: License :: OSI Approved :: MIT License
Classifier: Operating System :: OS Independent
Requires-Python: >=3.7
License-File: LICENSE
